pslearn/__init__.py
pslearn/feature_selection/__init__.py
pslearn/feature_selection/evaluation.py
pslearn/feature_selection/initilization.py
pslearn/feature_selection/topologies.py
pslearn/feature_selection/update.py
pslearn/hyperparameter_tuning/__init__.py
pslearn/hyperparameter_tuning/evaluation.py
pslearn/hyperparameter_tuning/initilization.py
pslearn/hyperparameter_tuning/topologies.py
pslearn/hyperparameter_tuning/update.py
pslearn-1.1.3.dist-info/LICENSE.txt
pslearn-1.1.3.dist-info/METADATA
pslearn-1.1.3.dist-info/WHEEL
pslearn-1.1.3.dist-info/top_level.txt
pslearn-1.1.3.dist-info/RECORD
