Metadata-Version: 2.1
Name: pslearn
Version: 1.1.3
Summary: Particle Swarm Optimization For Hyperparameter Tuning and Feature Selection.
Home-page: https://github.com/HindyDS/pslearn
Author: Hindy Yuen
Author-email: hindy888@hotmail.com
License: MIT
Keywords: machine learning Particle Swarm Optimization hyperparameters tuning feature selection
Platform: UNKNOWN
Classifier: Development Status :: 5 - Production/Stable
Classifier: Intended Audience :: Developers
Classifier: Topic :: Software Development :: Build Tools
Classifier: License :: OSI Approved :: MIT License
Classifier: Programming Language :: Python :: 3.7
Classifier: Programming Language :: Python :: 3.8
Classifier: Programming Language :: Python :: 3.9
Requires-Python: >=3.6
License-File: LICENSE.txt
